stellar_account_prometheus_exporter/__init__.py
stellar_account_prometheus_exporter/exporter.py
stellar_account_prometheus_exporter-0.0.8.dist-info/LICENSE
stellar_account_prometheus_exporter-0.0.8.dist-info/METADATA
stellar_account_prometheus_exporter-0.0.8.dist-info/WHEEL
stellar_account_prometheus_exporter-0.0.8.dist-info/entry_points.txt
stellar_account_prometheus_exporter-0.0.8.dist-info/top_level.txt
stellar_account_prometheus_exporter-0.0.8.dist-info/RECORD
