Metadata-Version: 2.1
Name: stellar-account-prometheus-exporter
Version: 0.0.8
Summary: Export stellar account balance in prometheus format
Home-page: https://github.com/stellar/stellar-account-prometheus-exporter
Author: Stellar Development Foundation
Author-email: ops@stellar.org
License: Apache Software License 2.0
Keywords: prometheus,exporter,stellar
Platform: UNKNOWN
Classifier: Development Status :: 3 - Alpha
Classifier: Programming Language :: Python :: 2
Classifier: Programming Language :: Python :: 3
Classifier: Intended Audience :: Information Technology
Classifier: Topic :: System :: Monitoring
Classifier: License :: OSI Approved :: Apache Software License
Requires-Dist: prometheus-client
Requires-Dist: pyyaml
Requires-Dist: requests
